cloudify_common_sdk/__init__.py
cloudify_common_sdk/exceptions.py
cloudify_common_sdk/filters.py
cloudify_common_sdk/ftp.py
cloudify_common_sdk/importer.py
cloudify_common_sdk/iso9660.py
cloudify_common_sdk/ovf.py
cloudify_common_sdk/resource_downloader.py
cloudify_rest_sdk/__init__.py
cloudify_rest_sdk/utility.py
cloudify_terminal_sdk/__init__.py
cloudify_terminal_sdk/base_connection.py
cloudify_terminal_sdk/netconf_connection.py
cloudify_terminal_sdk/terminal_connection.py
cloudify_utilities_plugins_sdk-0.0.20.dist-info/DESCRIPTION.rst
cloudify_utilities_plugins_sdk-0.0.20.dist-info/METADATA
cloudify_utilities_plugins_sdk-0.0.20.dist-info/RECORD
cloudify_utilities_plugins_sdk-0.0.20.dist-info/WHEEL
cloudify_utilities_plugins_sdk-0.0.20.dist-info/metadata.json
cloudify_utilities_plugins_sdk-0.0.20.dist-info/top_level.txt
